enigma/__init__.py
enigma/sat.py
enigma/sat_torch.py
enigma_sat-0.0.3.dist-info/LICENSE
enigma_sat-0.0.3.dist-info/METADATA
enigma_sat-0.0.3.dist-info/WHEEL
enigma_sat-0.0.3.dist-info/top_level.txt
enigma_sat-0.0.3.dist-info/RECORD
