Metadata-Version: 2.1
Name: enigma-sat
Version: 0.0.3
Summary: Enigma SAT-solver.
Home-page: https://github.com/joeyp722/Enigma
Author: joeyp722
Author-email: 
License: Apache-2.0 license
Classifier: License :: OSI Approved :: MIT License
Classifier: Programming Language :: Python :: 3
Classifier: Programming Language :: Python :: 3 :: Only
Classifier: Programming Language :: Python :: 3.6
Classifier: Programming Language :: Python :: 3.7
Classifier: Programming Language :: Python :: 3.8
Classifier: Programming Language :: Python :: 3.9
Classifier: Programming Language :: Python :: Implementation :: CPython
Classifier: Programming Language :: Python :: Implementation :: PyPy
Requires-Python: >=3.9.13
License-File: LICENSE
Requires-Dist: tokenize-rt (>=3.2.0)
Requires-Dist: tqdm
